spacybert/__init__.py
spacybert/about.py
tests/__init__.py
tests/test_bert_inference.py
spacybert-1.0.1.dist-info/LICENSE
spacybert-1.0.1.dist-info/METADATA
spacybert-1.0.1.dist-info/WHEEL
spacybert-1.0.1.dist-info/top_level.txt
spacybert-1.0.1.dist-info/RECORD
