Metadata-Version: 2.1
Name: spacybert
Version: 1.0.1
Summary: spaCy pipeline component for adding Bert embedding meta data to Doc, Token and Span objects.
Home-page: https://github.com/surajiyer/spacybert
Author: Suraj Iyer
Author-email: me@surajiyer.com
License: MIT
Platform: UNKNOWN
Requires-Dist: torch (>=1.4.0)
Requires-Dist: transformers (>=3.0.0)
Requires-Dist: spacy (<3.0.0,>=2.2.1)
Requires-Dist: spacy-langdetect (>=0.1.2)
